lsstseries/__init__.py
lsstseries/_version.py
lsstseries/ensemble.py
lsstseries/timeseries.py
lsstseries/analysis/__init__.py
lsstseries/analysis/stetsonj.py
lsstseries/analysis/structurefunction2.py
lsstseries-0.1.0.dist-info/LICENSE
lsstseries-0.1.0.dist-info/METADATA
lsstseries-0.1.0.dist-info/WHEEL
lsstseries-0.1.0.dist-info/top_level.txt
lsstseries-0.1.0.dist-info/RECORD
